asight/__init__.py
asight/__main__.py
asight/_version.py
asight/asight_wrapper/__init__.py
asight/asight_wrapper/asight_entrance.py
asight/common/__init__.py
asight/common/profiling/__init__.py
asight/common/profiling/profiling_info.py
asight/common/profiling/summary.py
asight/common/profiling/task_time.py
asight/config/__init__.py
asight/config/config.ini
asight/config/config.py
asight/datasets/__init__.py
asight/datasets/data_dir_dataset.py
asight/datasets/dataset.py
asight/datasets/profiling_dataset.py
asight/optimizer/__init__.py
asight/optimizer/operator_optimizer.py
asight/optimizer/optimizer.py
asight/optimizer/operator_checker/__init__.py
asight/optimizer/operator_checker/aicpu_checker.py
asight/optimizer/operator_checker/block_dim_checker.py
asight/optimizer/operator_checker/mte2_bound_checker.py
asight/optimizer/operator_checker/operator_bound_checker.py
asight/optimizer/operator_checker/operator_checker.py
asight/result/__init__.py
asight/result/optimize_result.py
asight/result/record.py
asight/result/record_item.py
asight/result/result.py
asight/util/__init__.py
asight/util/common.py
asight/util/excel.py
asight/util/log.py
asight/util/singleton.py
asight-0.1.2.dist-info/METADATA
asight-0.1.2.dist-info/WHEEL
asight-0.1.2.dist-info/entry_points.txt
asight-0.1.2.dist-info/top_level.txt
asight-0.1.2.dist-info/RECORD
