Metadata-Version: 2.1
Name: asight
Version: 0.1.2
Summary: Ascend Performance Analysis Tool.
Home-page: https://gitee.com/Ascend/Asight
Author: Zhu LiangYing
Author-email: zhuliangying@huawei.com
Maintainer: Zhu LiangYing
Maintainer-email: zhuliangying@huawei.com
License: UNKNOWN
Keywords: Asight
Platform: UNKNOWN
Classifier: Development Status :: 3 - Alpha
Classifier: Intended Audience :: Developers
Classifier: Natural Language :: Chinese (Simplified)
Classifier: Programming Language :: Python :: 3
Classifier: Programming Language :: Python :: 3.6
Classifier: Programming Language :: Python :: 3.7
Classifier: Programming Language :: Python :: 3.8
Classifier: Programming Language :: Python :: 3.9
Classifier: Programming Language :: Python :: 3.10
Requires-Python: >=3.6
Requires-Dist: xlsxwriter (>=0.3.6)
Provides-Extra: dev
Requires-Dist: mock ; extra == 'dev'
Requires-Dist: pytest ; extra == 'dev'
Requires-Dist: pytest-cov ; extra == 'dev'
Requires-Dist: pytest-flake8 ; extra == 'dev'
Requires-Dist: pytest-isort ; extra == 'dev'
Requires-Dist: pytest-mock ; extra == 'dev'
Requires-Dist: pytest-mypy ; extra == 'dev'
Requires-Dist: pytest-pycodestyle ; extra == 'dev'
Requires-Dist: pytest-pydocstyle ; extra == 'dev'
Requires-Dist: pytest-pylint ; extra == 'dev'
Requires-Dist: pytest-yapf3 ; extra == 'dev'
Requires-Dist: types-setuptools ; extra == 'dev'
Requires-Dist: xlrd (==1.2.0) ; extra == 'dev'
Requires-Dist: xlsxwriter ; extra == 'dev'
Requires-Dist: coverage (>=6.4.3) ; extra == 'dev'
Requires-Dist: flake8 (<5) ; extra == 'dev'
Requires-Dist: isort ; extra == 'dev'
Requires-Dist: mypy ; extra == 'dev'
Requires-Dist: pylint ; extra == 'dev'
Requires-Dist: yapf ; extra == 'dev'
